package com.tencent.smtt.net;

import java.util.HashMap;
import java.util.Iterator;
import java.util.Map.Entry;
import java.util.Set;
import java.util.Vector;

public class c
{
  private static PageVisitRecorder jdField_a_of_type_ComTencentSmttNetPageVisitRecorder;
  private static String jdField_a_of_type_JavaLangString;
  private static boolean jdField_a_of_type_Boolean = false;
  private static boolean b = true;
  private static boolean c = true;
  
  /* Error */
  public static void a()
  {
    // Byte code:
    //   0: getstatic 19	com/tencent/smtt/net/c:jdField_a_of_type_Boolean	Z
    //   3: ifeq +4 -> 7
    //   6: return
    //   7: invokestatic 25	com/tencent/smtt/webkit/ContextHolder:getInstance	()Lcom/tencent/smtt/webkit/ContextHolder;
    //   10: invokevirtual 29	com/tencent/smtt/webkit/ContextHolder:getApplicationContext	()Landroid/content/Context;
    //   13: ifnonnull +4 -> 17
    //   16: return
    //   17: invokestatic 25	com/tencent/smtt/webkit/ContextHolder:getInstance	()Lcom/tencent/smtt/webkit/ContextHolder;
    //   20: invokevirtual 29	com/tencent/smtt/webkit/ContextHolder:getApplicationContext	()Landroid/content/Context;
    //   23: invokevirtual 35	android/content/Context:getCacheDir	()Ljava/io/File;
    //   26: invokevirtual 41	java/io/File:getPath	()Ljava/lang/String;
    //   29: putstatic 43	com/tencent/smtt/net/c:jdField_a_of_type_JavaLangString	Ljava/lang/String;
    //   32: getstatic 43	com/tencent/smtt/net/c:jdField_a_of_type_JavaLangString	Ljava/lang/String;
    //   35: ldc 45
    //   37: invokevirtual 51	java/lang/String:endsWith	(Ljava/lang/String;)Z
    //   40: ifne +33 -> 73
    //   43: new 53	java/lang/StringBuilder
    //   46: dup
    //   47: invokespecial 56	java/lang/StringBuilder:<init>	()V
    //   50: astore_0
    //   51: aload_0
    //   52: getstatic 43	com/tencent/smtt/net/c:jdField_a_of_type_JavaLangString	Ljava/lang/String;
    //   55: invokevirtual 60	java/lang/StringBuilder:append	(Ljava/lang/String;)Ljava/lang/StringBuilder;
    //   58: pop
    //   59: aload_0
    //   60: ldc 45
    //   62: invokevirtual 60	java/lang/StringBuilder:append	(Ljava/lang/String;)Ljava/lang/StringBuilder;
    //   65: pop
    //   66: aload_0
    //   67: invokevirtual 63	java/lang/StringBuilder:toString	()Ljava/lang/String;
    //   70: putstatic 43	com/tencent/smtt/net/c:jdField_a_of_type_JavaLangString	Ljava/lang/String;
    //   73: new 53	java/lang/StringBuilder
    //   76: dup
    //   77: invokespecial 56	java/lang/StringBuilder:<init>	()V
    //   80: astore_0
    //   81: aload_0
    //   82: getstatic 43	com/tencent/smtt/net/c:jdField_a_of_type_JavaLangString	Ljava/lang/String;
    //   85: invokevirtual 60	java/lang/StringBuilder:append	(Ljava/lang/String;)Ljava/lang/StringBuilder;
    //   88: pop
    //   89: aload_0
    //   90: ldc 65
    //   92: invokevirtual 60	java/lang/StringBuilder:append	(Ljava/lang/String;)Ljava/lang/StringBuilder;
    //   95: pop
    //   96: aload_0
    //   97: invokevirtual 63	java/lang/StringBuilder:toString	()Ljava/lang/String;
    //   100: astore 6
    //   102: new 67	java/io/FileInputStream
    //   105: dup
    //   106: aload 6
    //   108: invokespecial 70	java/io/FileInputStream:<init>	(Ljava/lang/String;)V
    //   111: astore_0
    //   112: new 72	java/io/ObjectInputStream
    //   115: dup
    //   116: aload_0
    //   117: invokespecial 75	java/io/ObjectInputStream:<init>	(Ljava/io/InputStream;)V
    //   120: astore 5
    //   122: aload_0
    //   123: astore_2
    //   124: aload 5
    //   126: astore_3
    //   127: aload 5
    //   129: invokevirtual 79	java/io/ObjectInputStream:readObject	()Ljava/lang/Object;
    //   132: checkcast 81	com/tencent/smtt/net/PageVisitRecorder
    //   135: putstatic 83	com/tencent/smtt/net/c:jdField_a_of_type_ComTencentSmttNetPageVisitRecorder	Lcom/tencent/smtt/net/PageVisitRecorder;
    //   138: aload 5
    //   140: invokevirtual 86	java/io/ObjectInputStream:close	()V
    //   143: aload_0
    //   144: invokevirtual 87	java/io/FileInputStream:close	()V
    //   147: goto +116 -> 263
    //   150: astore 4
    //   152: aload_0
    //   153: astore_1
    //   154: aload 5
    //   156: astore_0
    //   157: goto +34 -> 191
    //   160: astore_1
    //   161: aconst_null
    //   162: astore_3
    //   163: goto +136 -> 299
    //   166: astore 4
    //   168: aconst_null
    //   169: astore_2
    //   170: aload_0
    //   171: astore_1
    //   172: aload_2
    //   173: astore_0
    //   174: goto +17 -> 191
    //   177: astore_1
    //   178: aconst_null
    //   179: astore_0
    //   180: aload_0
    //   181: astore_3
    //   182: goto +117 -> 299
    //   185: astore 4
    //   187: aconst_null
    //   188: astore_0
    //   189: aload_0
    //   190: astore_1
    //   191: aload_1
    //   192: astore_2
    //   193: aload_0
    //   194: astore_3
    //   195: aload 4
    //   197: invokevirtual 90	java/lang/Throwable:printStackTrace	()V
    //   200: aload_1
    //   201: astore_2
    //   202: aload_0
    //   203: astore_3
    //   204: new 37	java/io/File
    //   207: dup
    //   208: aload 6
    //   210: invokespecial 91	java/io/File:<init>	(Ljava/lang/String;)V
    //   213: astore 4
    //   215: aload_1
    //   216: astore_2
    //   217: aload_0
    //   218: astore_3
    //   219: aload 4
    //   221: invokevirtual 95	java/io/File:exists	()Z
    //   224: ifeq +13 -> 237
    //   227: aload_1
    //   228: astore_2
    //   229: aload_0
    //   230: astore_3
    //   231: aload 4
    //   233: invokevirtual 98	java/io/File:delete	()Z
    //   236: pop
    //   237: aload_0
    //   238: ifnull +10 -> 248
    //   241: aload_0
    //   242: invokevirtual 86	java/io/ObjectInputStream:close	()V
    //   245: goto +3 -> 248
    //   248: aload_1
    //   249: ifnull +14 -> 263
    //   252: aload_1
    //   253: invokevirtual 87	java/io/FileInputStream:close	()V
    //   256: goto +7 -> 263
    //   259: aload_0
    //   260: invokevirtual 90	java/lang/Throwable:printStackTrace	()V
    //   263: getstatic 83	com/tencent/smtt/net/c:jdField_a_of_type_ComTencentSmttNetPageVisitRecorder	Lcom/tencent/smtt/net/PageVisitRecorder;
    //   266: ifnonnull +13 -> 279
    //   269: new 81	com/tencent/smtt/net/PageVisitRecorder
    //   272: dup
    //   273: invokespecial 99	com/tencent/smtt/net/PageVisitRecorder:<init>	()V
    //   276: putstatic 83	com/tencent/smtt/net/c:jdField_a_of_type_ComTencentSmttNetPageVisitRecorder	Lcom/tencent/smtt/net/PageVisitRecorder;
    //   279: getstatic 83	com/tencent/smtt/net/c:jdField_a_of_type_ComTencentSmttNetPageVisitRecorder	Lcom/tencent/smtt/net/PageVisitRecorder;
    //   282: invokevirtual 102	com/tencent/smtt/net/PageVisitRecorder:init	()V
    //   285: getstatic 83	com/tencent/smtt/net/c:jdField_a_of_type_ComTencentSmttNetPageVisitRecorder	Lcom/tencent/smtt/net/PageVisitRecorder;
    //   288: invokevirtual 105	com/tencent/smtt/net/PageVisitRecorder:printToString	()V
    //   291: iconst_1
    //   292: putstatic 19	com/tencent/smtt/net/c:jdField_a_of_type_Boolean	Z
    //   295: return
    //   296: astore_1
    //   297: aload_2
    //   298: astore_0
    //   299: aload_3
    //   300: ifnull +10 -> 310
    //   303: aload_3
    //   304: invokevirtual 86	java/io/ObjectInputStream:close	()V
    //   307: goto +3 -> 310
    //   310: aload_0
    //   311: ifnull +14 -> 325
    //   314: aload_0
    //   315: invokevirtual 87	java/io/FileInputStream:close	()V
    //   318: goto +7 -> 325
    //   321: aload_0
    //   322: invokevirtual 90	java/lang/Throwable:printStackTrace	()V
    //   325: aload_1
    //   326: athrow
    //   327: astore_2
    //   328: goto -91 -> 237
    //   331: astore_0
    //   332: goto -73 -> 259
    //   335: astore_0
    //   336: goto -15 -> 321
    // Local variable table:
    //   start	length	slot	name	signature
    //   50	272	0	localObject1	Object
    //   331	1	0	localThrowable1	Throwable
    //   335	1	0	localThrowable2	Throwable
    //   153	1	1	localObject2	Object
    //   160	1	1	localObject3	Object
    //   171	1	1	localObject4	Object
    //   177	1	1	localObject5	Object
    //   190	63	1	localObject6	Object
    //   296	30	1	localObject7	Object
    //   123	175	2	localObject8	Object
    //   327	1	2	localThrowable3	Throwable
    //   126	178	3	localObject9	Object
    //   150	1	4	localThrowable4	Throwable
    //   166	1	4	localThrowable5	Throwable
    //   185	11	4	localThrowable6	Throwable
    //   213	19	4	localFile	java.io.File
    //   120	35	5	localObjectInputStream	java.io.ObjectInputStream
    //   100	109	6	str	String
    // Exception table:
    //   from	to	target	type
    //   127	138	150	java/lang/Throwable
    //   112	122	160	finally
    //   112	122	166	java/lang/Throwable
    //   102	112	177	finally
    //   102	112	185	java/lang/Throwable
    //   127	138	296	finally
    //   195	200	296	finally
    //   204	215	296	finally
    //   219	227	296	finally
    //   231	237	296	finally
    //   204	215	327	java/lang/Throwable
    //   219	227	327	java/lang/Throwable
    //   231	237	327	java/lang/Throwable
    //   138	147	331	java/lang/Throwable
    //   241	245	331	java/lang/Throwable
    //   252	256	331	java/lang/Throwable
    //   303	307	335	java/lang/Throwable
    //   314	318	335	java/lang/Throwable
  }
  
  public static void a(String paramString)
  {
    if (!jdField_a_of_type_Boolean)
    {
      a();
      if (!jdField_a_of_type_Boolean) {
        return;
      }
    }
    paramString = jdField_a_of_type_ComTencentSmttNetPageVisitRecorder.getPageTopHost(paramString);
    if (paramString != null)
    {
      if (paramString.size() == 0) {
        return;
      }
      paramString = paramString.iterator();
      while (paramString.hasNext()) {
        AwNetworkUtils.setPreConnect((String)paramString.next(), 1);
      }
      return;
    }
  }
  
  public static void a(String paramString, HashMap<String, String> paramHashMap)
  {
    if (!jdField_a_of_type_Boolean) {
      a();
    }
    if (jdField_a_of_type_Boolean)
    {
      if (jdField_a_of_type_ComTencentSmttNetPageVisitRecorder == null) {
        return;
      }
      Vector localVector = new Vector();
      paramHashMap = paramHashMap.entrySet().iterator();
      while (paramHashMap.hasNext())
      {
        Map.Entry localEntry = (Map.Entry)paramHashMap.next();
        if (((String)localEntry.getValue()).equals("0")) {
          localVector.add(localEntry.getKey());
        } else {
          jdField_a_of_type_ComTencentSmttNetPageVisitRecorder.onRequestSubResource((String)localEntry.getKey());
        }
      }
      jdField_a_of_type_ComTencentSmttNetPageVisitRecorder.onRequestUrl(paramString, localVector);
      return;
    }
  }
  
  /* Error */
  public static void b()
  {
    // Byte code:
    //   0: getstatic 19	com/tencent/smtt/net/c:jdField_a_of_type_Boolean	Z
    //   3: ifne +4 -> 7
    //   6: return
    //   7: getstatic 83	com/tencent/smtt/net/c:jdField_a_of_type_ComTencentSmttNetPageVisitRecorder	Lcom/tencent/smtt/net/PageVisitRecorder;
    //   10: ifnull +216 -> 226
    //   13: getstatic 43	com/tencent/smtt/net/c:jdField_a_of_type_JavaLangString	Ljava/lang/String;
    //   16: ifnonnull +4 -> 20
    //   19: return
    //   20: getstatic 174	com/tencent/smtt/net/c:c	Z
    //   23: ifeq +10 -> 33
    //   26: iconst_0
    //   27: putstatic 174	com/tencent/smtt/net/c:c	Z
    //   30: invokestatic 176	com/tencent/smtt/net/c:c	()V
    //   33: getstatic 83	com/tencent/smtt/net/c:jdField_a_of_type_ComTencentSmttNetPageVisitRecorder	Lcom/tencent/smtt/net/PageVisitRecorder;
    //   36: invokevirtual 105	com/tencent/smtt/net/PageVisitRecorder:printToString	()V
    //   39: new 53	java/lang/StringBuilder
    //   42: dup
    //   43: invokespecial 56	java/lang/StringBuilder:<init>	()V
    //   46: astore_0
    //   47: aload_0
    //   48: getstatic 43	com/tencent/smtt/net/c:jdField_a_of_type_JavaLangString	Ljava/lang/String;
    //   51: invokevirtual 60	java/lang/StringBuilder:append	(Ljava/lang/String;)Ljava/lang/StringBuilder;
    //   54: pop
    //   55: aload_0
    //   56: ldc 65
    //   58: invokevirtual 60	java/lang/StringBuilder:append	(Ljava/lang/String;)Ljava/lang/StringBuilder;
    //   61: pop
    //   62: aload_0
    //   63: invokevirtual 63	java/lang/StringBuilder:toString	()Ljava/lang/String;
    //   66: astore_0
    //   67: aconst_null
    //   68: astore_1
    //   69: aconst_null
    //   70: astore_2
    //   71: aconst_null
    //   72: astore 4
    //   74: new 178	java/io/FileOutputStream
    //   77: dup
    //   78: aload_0
    //   79: invokespecial 179	java/io/FileOutputStream:<init>	(Ljava/lang/String;)V
    //   82: astore_0
    //   83: aload_0
    //   84: astore_2
    //   85: new 181	java/io/ObjectOutputStream
    //   88: dup
    //   89: aload_0
    //   90: invokespecial 184	java/io/ObjectOutputStream:<init>	(Ljava/io/OutputStream;)V
    //   93: astore_3
    //   94: aload_3
    //   95: getstatic 83	com/tencent/smtt/net/c:jdField_a_of_type_ComTencentSmttNetPageVisitRecorder	Lcom/tencent/smtt/net/PageVisitRecorder;
    //   98: invokevirtual 188	java/io/ObjectOutputStream:writeObject	(Ljava/lang/Object;)V
    //   101: aload_3
    //   102: invokevirtual 189	java/io/ObjectOutputStream:close	()V
    //   105: aload_0
    //   106: invokevirtual 190	java/io/FileOutputStream:close	()V
    //   109: goto +68 -> 177
    //   112: astore_1
    //   113: aload_3
    //   114: astore_2
    //   115: goto +83 -> 198
    //   118: astore_1
    //   119: aload_3
    //   120: astore 4
    //   122: aload_1
    //   123: astore_3
    //   124: goto +16 -> 140
    //   127: astore_3
    //   128: goto +12 -> 140
    //   131: astore_1
    //   132: aconst_null
    //   133: astore_0
    //   134: goto +64 -> 198
    //   137: astore_3
    //   138: aconst_null
    //   139: astore_0
    //   140: aload 4
    //   142: astore_1
    //   143: aload_0
    //   144: astore_2
    //   145: aload_3
    //   146: invokevirtual 90	java/lang/Throwable:printStackTrace	()V
    //   149: aload 4
    //   151: ifnull +11 -> 162
    //   154: aload 4
    //   156: invokevirtual 189	java/io/ObjectOutputStream:close	()V
    //   159: goto +3 -> 162
    //   162: aload_0
    //   163: ifnull +14 -> 177
    //   166: aload_0
    //   167: invokevirtual 190	java/io/FileOutputStream:close	()V
    //   170: goto +7 -> 177
    //   173: aload_0
    //   174: invokevirtual 90	java/lang/Throwable:printStackTrace	()V
    //   177: getstatic 192	com/tencent/smtt/net/c:b	Z
    //   180: ifeq +10 -> 190
    //   183: invokestatic 195	com/tencent/smtt/net/c:d	()V
    //   186: iconst_0
    //   187: putstatic 192	com/tencent/smtt/net/c:b	Z
    //   190: return
    //   191: astore_3
    //   192: aload_2
    //   193: astore_0
    //   194: aload_1
    //   195: astore_2
    //   196: aload_3
    //   197: astore_1
    //   198: aload_2
    //   199: ifnull +10 -> 209
    //   202: aload_2
    //   203: invokevirtual 189	java/io/ObjectOutputStream:close	()V
    //   206: goto +3 -> 209
    //   209: aload_0
    //   210: ifnull +14 -> 224
    //   213: aload_0
    //   214: invokevirtual 190	java/io/FileOutputStream:close	()V
    //   217: goto +7 -> 224
    //   220: aload_0
    //   221: invokevirtual 90	java/lang/Throwable:printStackTrace	()V
    //   224: aload_1
    //   225: athrow
    //   226: return
    //   227: astore_0
    //   228: goto -55 -> 173
    //   231: astore_0
    //   232: goto -12 -> 220
    // Local variable table:
    //   start	length	slot	name	signature
    //   46	175	0	localObject1	Object
    //   227	1	0	localThrowable1	Throwable
    //   231	1	0	localThrowable2	Throwable
    //   68	1	1	localObject2	Object
    //   112	1	1	localObject3	Object
    //   118	5	1	localThrowable3	Throwable
    //   131	1	1	localObject4	Object
    //   142	83	1	localObject5	Object
    //   70	133	2	localObject6	Object
    //   93	31	3	localObject7	Object
    //   127	1	3	localThrowable4	Throwable
    //   137	9	3	localThrowable5	Throwable
    //   191	6	3	localObject8	Object
    //   72	83	4	localObject9	Object
    // Exception table:
    //   from	to	target	type
    //   94	101	112	finally
    //   94	101	118	java/lang/Throwable
    //   85	94	127	java/lang/Throwable
    //   74	83	131	finally
    //   74	83	137	java/lang/Throwable
    //   85	94	191	finally
    //   145	149	191	finally
    //   101	109	227	java/lang/Throwable
    //   154	159	227	java/lang/Throwable
    //   166	170	227	java/lang/Throwable
    //   202	206	231	java/lang/Throwable
    //   213	217	231	java/lang/Throwable
  }
  
  public static void c()
  {
    if (!c) {
      return;
    }
    if (!jdField_a_of_type_Boolean) {
      a();
    }
    if (jdField_a_of_type_Boolean)
    {
      Object localObject = jdField_a_of_type_ComTencentSmttNetPageVisitRecorder;
      if (localObject == null) {
        return;
      }
      localObject = ((PageVisitRecorder)localObject).getTopMainResource();
      if (localObject != null)
      {
        if (((Vector)localObject).size() == 0) {
          return;
        }
        localObject = ((Vector)localObject).iterator();
        while (((Iterator)localObject).hasNext()) {
          AwNetworkUtils.setPreConnect((String)((Iterator)localObject).next(), 1);
        }
        c = false;
        return;
      }
      return;
    }
  }
  
  /* Error */
  public static void d()
  {
    // Byte code:
    //   0: getstatic 19	com/tencent/smtt/net/c:jdField_a_of_type_Boolean	Z
    //   3: ifeq +359 -> 362
    //   6: getstatic 83	com/tencent/smtt/net/c:jdField_a_of_type_ComTencentSmttNetPageVisitRecorder	Lcom/tencent/smtt/net/PageVisitRecorder;
    //   9: astore_1
    //   10: aload_1
    //   11: ifnonnull +4 -> 15
    //   14: return
    //   15: aload_1
    //   16: invokevirtual 202	com/tencent/smtt/net/PageVisitRecorder:getTopSubResource	()Ljava/util/Vector;
    //   19: astore_2
    //   20: aload_2
    //   21: ifnull +340 -> 361
    //   24: aload_2
    //   25: invokevirtual 117	java/util/Vector:size	()I
    //   28: ifne +4 -> 32
    //   31: return
    //   32: new 53	java/lang/StringBuilder
    //   35: dup
    //   36: invokespecial 56	java/lang/StringBuilder:<init>	()V
    //   39: astore_1
    //   40: aload_1
    //   41: getstatic 43	com/tencent/smtt/net/c:jdField_a_of_type_JavaLangString	Ljava/lang/String;
    //   44: invokevirtual 60	java/lang/StringBuilder:append	(Ljava/lang/String;)Ljava/lang/StringBuilder;
    //   47: pop
    //   48: aload_1
    //   49: ldc -52
    //   51: invokevirtual 60	java/lang/StringBuilder:append	(Ljava/lang/String;)Ljava/lang/StringBuilder;
    //   54: pop
    //   55: new 37	java/io/File
    //   58: dup
    //   59: aload_1
    //   60: invokevirtual 63	java/lang/StringBuilder:toString	()Ljava/lang/String;
    //   63: invokespecial 91	java/io/File:<init>	(Ljava/lang/String;)V
    //   66: astore_1
    //   67: new 178	java/io/FileOutputStream
    //   70: dup
    //   71: aload_1
    //   72: invokespecial 207	java/io/FileOutputStream:<init>	(Ljava/io/File;)V
    //   75: astore_1
    //   76: new 53	java/lang/StringBuilder
    //   79: dup
    //   80: ldc -47
    //   82: invokespecial 210	java/lang/StringBuilder:<init>	(Ljava/lang/String;)V
    //   85: astore_3
    //   86: new 212	java/util/Date
    //   89: dup
    //   90: invokespecial 213	java/util/Date:<init>	()V
    //   93: astore 4
    //   95: new 215	java/text/SimpleDateFormat
    //   98: dup
    //   99: ldc -39
    //   101: invokespecial 218	java/text/SimpleDateFormat:<init>	(Ljava/lang/String;)V
    //   104: aload 4
    //   106: invokevirtual 222	java/text/SimpleDateFormat:format	(Ljava/util/Date;)Ljava/lang/String;
    //   109: astore 4
    //   111: aload_3
    //   112: ldc -32
    //   114: invokevirtual 60	java/lang/StringBuilder:append	(Ljava/lang/String;)Ljava/lang/StringBuilder;
    //   117: pop
    //   118: aload_3
    //   119: aload 4
    //   121: invokevirtual 60	java/lang/StringBuilder:append	(Ljava/lang/String;)Ljava/lang/StringBuilder;
    //   124: pop
    //   125: aload_3
    //   126: ldc -30
    //   128: invokevirtual 60	java/lang/StringBuilder:append	(Ljava/lang/String;)Ljava/lang/StringBuilder;
    //   131: pop
    //   132: aload_3
    //   133: ldc -28
    //   135: invokevirtual 60	java/lang/StringBuilder:append	(Ljava/lang/String;)Ljava/lang/StringBuilder;
    //   138: pop
    //   139: aload_3
    //   140: ldc -26
    //   142: invokevirtual 60	java/lang/StringBuilder:append	(Ljava/lang/String;)Ljava/lang/StringBuilder;
    //   145: pop
    //   146: aload_3
    //   147: ldc -28
    //   149: invokevirtual 60	java/lang/StringBuilder:append	(Ljava/lang/String;)Ljava/lang/StringBuilder;
    //   152: pop
    //   153: aload_3
    //   154: ldc -24
    //   156: invokevirtual 60	java/lang/StringBuilder:append	(Ljava/lang/String;)Ljava/lang/StringBuilder;
    //   159: pop
    //   160: iconst_0
    //   161: istore_0
    //   162: iload_0
    //   163: aload_2
    //   164: invokevirtual 117	java/util/Vector:size	()I
    //   167: if_icmpge +59 -> 226
    //   170: new 53	java/lang/StringBuilder
    //   173: dup
    //   174: invokespecial 56	java/lang/StringBuilder:<init>	()V
    //   177: astore 4
    //   179: aload 4
    //   181: ldc -22
    //   183: invokevirtual 60	java/lang/StringBuilder:append	(Ljava/lang/String;)Ljava/lang/StringBuilder;
    //   186: pop
    //   187: aload 4
    //   189: aload_2
    //   190: iload_0
    //   191: invokevirtual 238	java/util/Vector:get	(I)Ljava/lang/Object;
    //   194: checkcast 47	java/lang/String
    //   197: invokevirtual 60	java/lang/StringBuilder:append	(Ljava/lang/String;)Ljava/lang/StringBuilder;
    //   200: pop
    //   201: aload 4
    //   203: ldc -16
    //   205: invokevirtual 60	java/lang/StringBuilder:append	(Ljava/lang/String;)Ljava/lang/StringBuilder;
    //   208: pop
    //   209: aload_3
    //   210: aload 4
    //   212: invokevirtual 63	java/lang/StringBuilder:toString	()Ljava/lang/String;
    //   215: invokevirtual 60	java/lang/StringBuilder:append	(Ljava/lang/String;)Ljava/lang/StringBuilder;
    //   218: pop
    //   219: iload_0
    //   220: iconst_1
    //   221: iadd
    //   222: istore_0
    //   223: goto -61 -> 162
    //   226: aload_3
    //   227: aload_3
    //   228: invokevirtual 243	java/lang/StringBuilder:length	()I
    //   231: iconst_1
    //   232: isub
    //   233: invokevirtual 247	java/lang/StringBuilder:deleteCharAt	(I)Ljava/lang/StringBuilder;
    //   236: pop
    //   237: aload_3
    //   238: ldc -7
    //   240: invokevirtual 60	java/lang/StringBuilder:append	(Ljava/lang/String;)Ljava/lang/StringBuilder;
    //   243: pop
    //   244: aload_3
    //   245: ldc -5
    //   247: invokevirtual 60	java/lang/StringBuilder:append	(Ljava/lang/String;)Ljava/lang/StringBuilder;
    //   250: pop
    //   251: aload_3
    //   252: ldc -3
    //   254: invokevirtual 60	java/lang/StringBuilder:append	(Ljava/lang/String;)Ljava/lang/StringBuilder;
    //   257: pop
    //   258: aload_3
    //   259: ldc -1
    //   261: invokevirtual 60	java/lang/StringBuilder:append	(Ljava/lang/String;)Ljava/lang/StringBuilder;
    //   264: pop
    //   265: aload_3
    //   266: ldc_w 257
    //   269: invokevirtual 60	java/lang/StringBuilder:append	(Ljava/lang/String;)Ljava/lang/StringBuilder;
    //   272: pop
    //   273: aload_3
    //   274: ldc_w 259
    //   277: invokevirtual 60	java/lang/StringBuilder:append	(Ljava/lang/String;)Ljava/lang/StringBuilder;
    //   280: pop
    //   281: aload_3
    //   282: ldc_w 261
    //   285: invokevirtual 60	java/lang/StringBuilder:append	(Ljava/lang/String;)Ljava/lang/StringBuilder;
    //   288: pop
    //   289: aload_3
    //   290: ldc_w 263
    //   293: invokevirtual 60	java/lang/StringBuilder:append	(Ljava/lang/String;)Ljava/lang/StringBuilder;
    //   296: pop
    //   297: aload_1
    //   298: aload_3
    //   299: invokevirtual 63	java/lang/StringBuilder:toString	()Ljava/lang/String;
    //   302: invokevirtual 267	java/lang/String:getBytes	()[B
    //   305: invokevirtual 271	java/io/FileOutputStream:write	([B)V
    //   308: aload_1
    //   309: invokevirtual 190	java/io/FileOutputStream:close	()V
    //   312: return
    //   313: astore_1
    //   314: aload_1
    //   315: invokevirtual 90	java/lang/Throwable:printStackTrace	()V
    //   318: return
    //   319: astore_2
    //   320: goto +6 -> 326
    //   323: astore_2
    //   324: aconst_null
    //   325: astore_1
    //   326: aload_1
    //   327: ifnull +15 -> 342
    //   330: aload_1
    //   331: invokevirtual 190	java/io/FileOutputStream:close	()V
    //   334: goto +8 -> 342
    //   337: astore_1
    //   338: aload_1
    //   339: invokevirtual 90	java/lang/Throwable:printStackTrace	()V
    //   342: aload_2
    //   343: athrow
    //   344: aconst_null
    //   345: astore_1
    //   346: aload_1
    //   347: ifnull +13 -> 360
    //   350: aload_1
    //   351: invokevirtual 190	java/io/FileOutputStream:close	()V
    //   354: return
    //   355: astore_1
    //   356: aload_1
    //   357: invokevirtual 90	java/lang/Throwable:printStackTrace	()V
    //   360: return
    //   361: return
    //   362: return
    //   363: astore_1
    //   364: goto -20 -> 344
    //   367: astore_2
    //   368: goto -22 -> 346
    // Local variable table:
    //   start	length	slot	name	signature
    //   161	62	0	i	int
    //   9	300	1	localObject1	Object
    //   313	2	1	localThrowable1	Throwable
    //   325	6	1	localObject2	Object
    //   337	2	1	localThrowable2	Throwable
    //   345	6	1	localObject3	Object
    //   355	2	1	localThrowable3	Throwable
    //   363	1	1	localThrowable4	Throwable
    //   19	171	2	localVector	Vector
    //   319	1	2	localObject4	Object
    //   323	20	2	localObject5	Object
    //   367	1	2	localThrowable5	Throwable
    //   85	214	3	localStringBuilder	StringBuilder
    //   93	118	4	localObject6	Object
    // Exception table:
    //   from	to	target	type
    //   308	312	313	java/lang/Throwable
    //   76	160	319	finally
    //   162	219	319	finally
    //   226	308	319	finally
    //   67	76	323	finally
    //   330	334	337	java/lang/Throwable
    //   350	354	355	java/lang/Throwable
    //   67	76	363	java/lang/Throwable
    //   76	160	367	java/lang/Throwable
    //   162	219	367	java/lang/Throwable
    //   226	308	367	java/lang/Throwable
  }
}


/* Location:              C:\Users\Administrator\Desktop\学习资料\dex2jar\dex2jar-2.0\classes-dex2jar.jar!\com\tencent\smtt\net\c.class
 * Java compiler version: 6 (50.0)
 * JD-Core Version:       0.7.1
 */