package com.tencent.turingfd.sdk.tbs;

public final class b
  extends Thread
{
  /* Error */
  public b(c.a parama, android.content.Context paramContext)
  {
    // Byte code:
    //   0: aload_0
    //   1: aload_1
    //   2: putfield 11	com/tencent/turingfd/sdk/tbs/b:jdField_a_of_type_ComTencentTuringfdSdkTbsC$a	Lcom/tencent/turingfd/sdk/tbs/c$a;
    //   5: aload_0
    //   6: aload_2
    //   7: putfield 13	com/tencent/turingfd/sdk/tbs/b:jdField_a_of_type_AndroidContentContext	Landroid/content/Context;
    //   10: aload_0
    //   11: invokespecial 16	java/lang/Thread:<init>	()V
    //   14: return
    // Local variable table:
    //   start	length	slot	name	signature
    //   0	15	0	this	b
    //   0	15	1	parama	c.a
    //   0	15	2	paramContext	android.content.Context
  }
  
  public void run()
  {
    this.jdField_a_of_type_ComTencentTuringfdSdkTbsC$a.a.a(this.jdField_a_of_type_AndroidContentContext);
  }
}


/* Location:              C:\Users\Administrator\Desktop\学习资料\dex2jar\dex2jar-2.0\classes-dex2jar.jar!\com\tencent\turingfd\sdk\tbs\b.class
 * Java compiler version: 6 (50.0)
 * JD-Core Version:       0.7.1
 */